{
    "c2dictionary": true,
    "data": {
        "GenericNode": "Unidentified.%No information available.",
        "EntryNode": "Entry node.%If this node is taken, you lose connection and must restart.",
        "RelayNode": "Relay node.%Intermediate directory to relay a signal.",
        "GoalNode": "Goal node.%Whole network is controlled by the owner of this node.",
        "EncryptedNode": "Encrypted node.%Needs the right tool to be unlocked.",
        "FirewallNode": "Firewall node.%Hardens linked nodes, leading to slower hacking times.",
        "TracerNode": "Tracer node.%Increases the suspicion level of neighboring nodes.",
        "HunterNode": "Hunter node.%An antivirus. Tries to take your entry node and kick you out of the net.",
        "HoneypotNode": "Honeypot node.%Triggers every security system available in the network.",
        "DataNode": "Data node.%Contains credits you can secure by beating the level.",
        "BinaryNode": "Binary node.%Holds decryption software you can deploy.",
        "BandwidthNode": "Bandwidth node.%Increases the network speed of the owner.",
        "IntelNode": "Intel node.%Discloses the type of all unidentified nodes."
    }
}